Metadata-Version: 2.1
Name: metagpt-simple
Version: 0.8.1.20241029
Summary: The Multi-Agent Framework
Home-page: https://github.com/geekan/MetaGPT
License: MIT
Keywords: metagpt,multi-agent,multi-role,programming,gpt,llm,metaprogramming
Author: Alexander Wu
Author-email: alexanderwu@deepwisdom.ai
Requires-Python: >=3.9,<4.0
Classifier: License :: OSI Approved :: MIT License
Classifier: Programming Language :: Python :: 3
Classifier: Programming Language :: Python :: 3.9
Classifier: Programming Language :: Python :: 3.10
Classifier: Programming Language :: Python :: 3.11
Classifier: Programming Language :: Python :: 3.12
Classifier: Programming Language :: Python :: 3.13
Provides-Extra: android-assistant
Provides-Extra: dev
Provides-Extra: ocr
Provides-Extra: pyppeteer
Provides-Extra: rag
Provides-Extra: search-ddg
Provides-Extra: search-google
Provides-Extra: selenium
Provides-Extra: test
Requires-Dist: Pillow
Requires-Dist: PyYAML
Requires-Dist: agentops
Requires-Dist: aiofiles
Requires-Dist: aiohttp
Requires-Dist: anthropic
Requires-Dist: anytree
Requires-Dist: beautifulsoup4 ; extra == "selenium"
Requires-Dist: boto3
Requires-Dist: channels
Requires-Dist: curl-cffi
Requires-Dist: dashscope
Requires-Dist: faiss_cpu
Requires-Dist: fire
Requires-Dist: gitignore-parser
Requires-Dist: gitpython
Requires-Dist: google-generativeai
Requires-Dist: gymnasium
Requires-Dist: httplib2
Requires-Dist: imap_tools
Requires-Dist: ipykernel
Requires-Dist: ipython
Requires-Dist: ipywidgets
Requires-Dist: jieba
Requires-Dist: lancedb
Requires-Dist: libcst
Requires-Dist: loguru
Requires-Dist: meilisearch
Requires-Dist: nbclient
Requires-Dist: nbformat
Requires-Dist: networkx
Requires-Dist: numpy
Requires-Dist: openai
Requires-Dist: openpyxl
Requires-Dist: pandas
Requires-Dist: playwright
Requires-Dist: pydantic
Requires-Dist: python_docx
Requires-Dist: qdrant-client
Requires-Dist: qianfan
Requires-Dist: rank-bm25
Requires-Dist: redis
Requires-Dist: rich
Requires-Dist: scikit_learn
Requires-Dist: semantic-kernel
Requires-Dist: semantic_kernel
Requires-Dist: setuptools
Requires-Dist: socksio
Requires-Dist: spark_ai_python
Requires-Dist: ta
Requires-Dist: tenacity
Requires-Dist: tiktoken
Requires-Dist: tqdm
Requires-Dist: typer
Requires-Dist: typing-extensions
Requires-Dist: typing-inspect
Requires-Dist: volcengine-python-sdk
Requires-Dist: websocket-client
Requires-Dist: websockets
Requires-Dist: wrapt
Requires-Dist: zhipuai
Project-URL: Repository, https://github.com/geekan/MetaGPT
